helloworldbasic5message/__init__.py
helloworldbasic5message/mymessage.py
helloworldbasic5message/prev__init__.py
helloworldbasic5message/_previousinit/__init__.py
helloworldbasic5message/_previousinit/prev__init__.py
helloworldbasic5message-1.0.12.dist-info/METADATA
helloworldbasic5message-1.0.12.dist-info/WHEEL
helloworldbasic5message-1.0.12.dist-info/top_level.txt
helloworldbasic5message-1.0.12.dist-info/RECORD
